{"id": "961aad0a-a2d0-4752-9481-0842971c7306", "player_home": "PLAYER", "player_away": "Rhys Evans", "legs_to_win": 5, "sets_to_win": 1, "winner": "Rhys Evans", "log": [[{"player": "PLAYER", "points_scored": 26, "remaining_points": 475, "darts_thrown": 3, "fields": ""}, {"player": "Rhys Evans", "points_scored": 41, "remaining_points": 460, "darts_thrown": 3, "fields": "20,1,20"}, {"player": "PLAYER", "points_scored": 41, "remaining_points": 434, "darts_thrown": 3, "fields": ""}, {"player": "Rhys Evans", "points_scored": 98, "remaining_points": 362, "darts_thrown": 3, "fields": "T20,20,18"}, {"player": "PLAYER", "points_scored": 8, "remaining_points": 426, "darts_thrown": 3, "fields": ""}, {"player": "Rhys Evans", "points_scored": 41, "remaining_points": 321, "darts_thrown": 3, "fields": "20,20,1"}, {"player": "PLAYER", "points_scored": 47, "remaining_points": 379, "darts_thrown": 3, "fields": ""}, {"player": "Rhys Evans", "points_scored": 103, "remaining_points": 218, "darts_thrown": 3, "fields": "T1,D20,T20"}, {"player": "PLAYER", "points_scored": 14, "remaining_points": 365, "darts_thrown": 3, "fields": ""}, {"player": "Rhys Evans", "points_scored": 26, "remaining_points": 192, "darts_thrown": 3, "fields": "1,20,5"}, {"player": "PLAYER", "points_scored": 35, "remaining_points": 330, "darts_thrown": 3, "fields": ""}, {"player": "Rhys Evans", "points_scored": 32, "remaining_points": 160, "darts_thrown": 3, "fields": "5,T5,12"}, {"player": "PLAYER", "points_scored": 28, "remaining_points": 302, "darts_thrown": 3, "fields": ""}, {"player": "Rhys Evans", "points_scored": 26, "remaining_points": 134, "darts_thrown": 3, "fields": "5,1,20"}, {"player": "PLAYER", "points_scored": 17, "remaining_points": 285, "darts_thrown": 3, "fields": ""}, {"player": "Rhys Evans", "points_scored": 36, "remaining_points": 98, "darts_thrown": 3, "fields": "20,1,T5"}, {"player": "PLAYER", "points_scored": 45, "remaining_points": 240, "darts_thrown": 3, "fields": ""}, {"player": "Rhys Evans", "points_scored": 62, "remaining_points": 36, "darts_thrown": 3, "fields": "5,T19,0"}, {"player": "PLAYER", "points_scored": 67, "remaining_points": 173, "darts_thrown": 3, "fields": ""}, {"player": "Rhys Evans", "points_scored": 27, "remaining_points": 9, "darts_thrown": 3, "fields": "0,18,9"}, {"player": "PLAYER", "points_scored": 40, "remaining_points": 133, "darts_thrown": 3, "fields": ""}, {"player": "Rhys Evans", "points_scored": 7, "remaining_points": 2, "darts_thrown": 3, "fields": "D1,3,2"}, {"player": "PLAYER", "points_scored": 47, "remaining_points": 86, "darts_thrown": 3, "fields": ""}, {"player": "Rhys Evans", "points_scored": 0, "remaining_points": 2, "darts_thrown": 3, "fields": "0,0,1"}, {"player": "PLAYER", "points_scored": 22, "remaining_points": 64, "darts_thrown": 3, "fields": ""}, {"player": "Rhys Evans", "points_scored": 0, "remaining_points": 2, "darts_thrown": 3, "fields": "0,18"}, {"player": "PLAYER", "points_scored": 26, "remaining_points": 38, "darts_thrown": 3, "fields": ""}, {"player": "Rhys Evans", "points_scored": 0, "remaining_points": 2, "darts_thrown": 3, "fields": "0,1"}, {"player": "PLAYER", "points_scored": 30, "remaining_points": 8, "darts_thrown": 3, "fields": ""}, {"player": "Rhys Evans", "points_scored": 0, "remaining_points": 2, "darts_thrown": 3, "fields": "0,0,1"}, {"player": "PLAYER", "points_scored": 0, "remaining_points": 8, "darts_thrown": 3, "fields": ""}, {"player": "Rhys Evans", "points_scored": 0, "remaining_points": 2, "darts_thrown": 3, "fields": "0,18"}, {"player": "PLAYER", "points_scored": 0, "remaining_points": 8, "darts_thrown": 3, "fields": ""}, {"player": "Rhys Evans", "points_scored": 2, "remaining_points": 0, "darts_thrown": 1, "fields": "D1"}], [{"player": "Rhys Evans", "points_scored": 41, "remaining_points": 460, "darts_thrown": 3, "fields": "20,1,20"}, {"player": "PLAYER", "points_scored": 77, "remaining_points": 424, "darts_thrown": 3, "fields": ""}, {"player": "Rhys Evans", "points_scored": 40, "remaining_points": 420, "darts_thrown": 3, "fields": "T5,5,20"}, {"player": "PLAYER", "points_scored": 58, "remaining_points": 366, "darts_thrown": 3, "fields": ""}, {"player": "Rhys Evans", "points_scored": 26, "remaining_points": 394, "darts_thrown": 3, "fields": "1,5,20"}, {"player": "PLAYER", "points_scored": 29, "remaining_points": 337, "darts_thrown": 3, "fields": ""}, {"player": "Rhys Evans", "points_scored": 43, "remaining_points": 351, "darts_thrown": 3, "fields": "20,18,5"}, {"player": "PLAYER", "points_scored": 32, "remaining_points": 305, "darts_thrown": 3, "fields": ""}, {"player": "Rhys Evans", "points_scored": 85, "remaining_points": 266, "darts_thrown": 3, "fields": "5,T20,20"}, {"player": "PLAYER", "points_scored": 22, "remaining_points": 283, "darts_thrown": 3, "fields": ""}, {"player": "Rhys Evans", "points_scored": 21, "remaining_points": 245, "darts_thrown": 3, "fields": "T5,5,1"}, {"player": "PLAYER", "points_scored": 98, "remaining_points": 185, "darts_thrown": 3, "fields": ""}, {"player": "Rhys Evans", "points_scored": 26, "remaining_points": 219, "darts_thrown": 3, "fields": "1,5,20"}, {"player": "PLAYER", "points_scored": 58, "remaining_points": 127, "darts_thrown": 3, "fields": ""}, {"player": "Rhys Evans", "points_scored": 26, "remaining_points": 193, "darts_thrown": 3, "fields": "20,1,5"}, {"player": "PLAYER", "points_scored": 68, "remaining_points": 59, "darts_thrown": 3, "fields": ""}, {"player": "Rhys Evans", "points_scored": 31, "remaining_points": 162, "darts_thrown": 3, "fields": "1,20,D5"}, {"player": "PLAYER", "points_scored": 27, "remaining_points": 32, "darts_thrown": 3, "fields": ""}, {"player": "Rhys Evans", "points_scored": 52, "remaining_points": 110, "darts_thrown": 3, "fields": "20,20,T4"}, {"player": "PLAYER", "points_scored": 0, "remaining_points": 32, "darts_thrown": 3, "fields": ""}, {"player": "Rhys Evans", "points_scored": 26, "remaining_points": 84, "darts_thrown": 3, "fields": "5,1,20"}, {"player": "PLAYER", "points_scored": 8, "remaining_points": 24, "darts_thrown": 3, "fields": ""}, {"player": "Rhys Evans", "points_scored": 52, "remaining_points": 32, "darts_thrown": 3, "fields": "T16,4,0"}, {"player": "PLAYER", "points_scored": 0, "remaining_points": 24, "darts_thrown": 3, "fields": ""}, {"player": "Rhys Evans", "points_scored": 24, "remaining_points": 8, "darts_thrown": 3, "fields": "16,0,8"}, {"player": "PLAYER", "points_scored": 21, "remaining_points": 3, "darts_thrown": 3, "fields": ""}, {"player": "Rhys Evans", "points_scored": 0, "remaining_points": 8, "darts_thrown": 3, "fields": "0,18"}, {"player": "PLAYER", "points_scored": 0, "remaining_points": 3, "darts_thrown": 3, "fields": ""}, {"player": "Rhys Evans", "points_scored": 8, "remaining_points": 0, "darts_thrown": 1, "fields": "D4"}], [{"player": "PLAYER", "points_scored": 7, "remaining_points": 494, "darts_thrown": 3, "fields": ""}, {"player": "Rhys Evans", "points_scored": 45, "remaining_points": 456, "darts_thrown": 3, "fields": "5,20,20"}, {"player": "PLAYER", "points_scored": 79, "remaining_points": 415, "darts_thrown": 3, "fields": ""}, {"player": "Rhys Evans", "points_scored": 85, "remaining_points": 371, "darts_thrown": 3, "fields": "20,5,T20"}, {"player": "PLAYER", "points_scored": 30, "remaining_points": 385, "darts_thrown": 3, "fields": ""}, {"player": "Rhys Evans", "points_scored": 45, "remaining_points": 326, "darts_thrown": 3, "fields": "20,20,5"}, {"player": "PLAYER", "points_scored": 29, "remaining_points": 356, "darts_thrown": 3, "fields": ""}, {"player": "Rhys Evans", "points_scored": 36, "remaining_points": 290, "darts_thrown": 3, "fields": "T5,1,20"}, {"player": "PLAYER", "points_scored": 52, "remaining_points": 304, "darts_thrown": 3, "fields": ""}, {"player": "Rhys Evans", "points_scored": 41, "remaining_points": 249, "darts_thrown": 3, "fields": "20,20,1"}, {"player": "PLAYER", "points_scored": 45, "remaining_points": 259, "darts_thrown": 3, "fields": ""}, {"player": "Rhys Evans", "points_scored": 75, "remaining_points": 174, "darts_thrown": 3, "fields": "18,T18,T1"}, {"player": "PLAYER", "points_scored": 45, "remaining_points": 214, "darts_thrown": 3, "fields": ""}, {"player": "Rhys Evans", "points_scored": 41, "remaining_points": 133, "darts_thrown": 3, "fields": "20,20,1"}, {"player": "PLAYER", "points_scored": 40, "remaining_points": 174, "darts_thrown": 3, "fields": ""}, {"player": "Rhys Evans", "points_scored": 45, "remaining_points": 88, "darts_thrown": 3, "fields": "5,20,20"}, {"player": "PLAYER", "points_scored": 59, "remaining_points": 115, "darts_thrown": 3, "fields": ""}, {"player": "Rhys Evans", "points_scored": 48, "remaining_points": 40, "darts_thrown": 3, "fields": "16,16,16"}, {"player": "PLAYER", "points_scored": 21, "remaining_points": 94, "darts_thrown": 3, "fields": ""}, {"player": "Rhys Evans", "points_scored": 8, "remaining_points": 32, "darts_thrown": 3, "fields": "0,1,7"}, {"player": "PLAYER", "points_scored": 24, "remaining_points": 70, "darts_thrown": 3, "fields": ""}, {"player": "Rhys Evans", "points_scored": 32, "remaining_points": 0, "darts_thrown": 3, "fields": "0,0,D16"}], [{"player": "Rhys Evans", "points_scored": 28, "remaining_points": 473, "darts_thrown": 3, "fields": "18,5,5"}, {"player": "PLAYER", "points_scored": 23, "remaining_points": 478, "darts_thrown": 3, "fields": ""}, {"player": "Rhys Evans", "points_scored": 85, "remaining_points": 388, "darts_thrown": 3, "fields": "20,5,T20"}, {"player": "PLAYER", "points_scored": 21, "remaining_points": 457, "darts_thrown": 3, "fields": ""}, {"player": "Rhys Evans", "points_scored": 60, "remaining_points": 328, "darts_thrown": 3, "fields": "20,20,20"}, {"player": "PLAYER", "points_scored": 29, "remaining_points": 428, "darts_thrown": 3, "fields": ""}, {"player": "Rhys Evans", "points_scored": 44, "remaining_points": 284, "darts_thrown": 3, "fields": "12,12,20"}, {"player": "PLAYER", "points_scored": 41, "remaining_points": 387, "darts_thrown": 3, "fields": ""}, {"player": "Rhys Evans", "points_scored": 45, "remaining_points": 239, "darts_thrown": 3, "fields": "5,20,20"}, {"player": "PLAYER", "points_scored": 65, "remaining_points": 322, "darts_thrown": 3, "fields": ""}, {"player": "Rhys Evans", "points_scored": 12, "remaining_points": 227, "darts_thrown": 3, "fields": "T1,5,4"}, {"player": "PLAYER", "points_scored": 28, "remaining_points": 294, "darts_thrown": 3, "fields": ""}, {"player": "Rhys Evans", "points_scored": 41, "remaining_points": 186, "darts_thrown": 3, "fields": "20,20,1"}, {"player": "PLAYER", "points_scored": 81, "remaining_points": 213, "darts_thrown": 3, "fields": ""}, {"player": "Rhys Evans", "points_scored": 30, "remaining_points": 156, "darts_thrown": 3, "fields": "5,20,5"}, {"player": "PLAYER", "points_scored": 68, "remaining_points": 145, "darts_thrown": 3, "fields": ""}, {"player": "Rhys Evans", "points_scored": 82, "remaining_points": 74, "darts_thrown": 3, "fields": "T20,5,17"}, {"player": "PLAYER", "points_scored": 41, "remaining_points": 104, "darts_thrown": 3, "fields": ""}, {"player": "Rhys Evans", "points_scored": 61, "remaining_points": 13, "darts_thrown": 3, "fields": "T11,0,D14"}, {"player": "PLAYER", "points_scored": 17, "remaining_points": 87, "darts_thrown": 3, "fields": ""}, {"player": "Rhys Evans", "points_scored": 9, "remaining_points": 4, "darts_thrown": 3, "fields": "5,0,4"}, {"player": "PLAYER", "points_scored": 55, "remaining_points": 32, "darts_thrown": 3, "fields": ""}, {"player": "Rhys Evans", "points_scored": 0, "remaining_points": 4, "darts_thrown": 3, "fields": "0,0,0"}, {"player": "PLAYER", "points_scored": 32, "remaining_points": 0, "darts_thrown": 2, "fields": ""}], [{"player": "PLAYER", "points_scored": 58, "remaining_points": 443, "darts_thrown": 3, "fields": ""}, {"player": "Rhys Evans", "points_scored": 35, "remaining_points": 466, "darts_thrown": 3, "fields": "12,20,T1"}, {"player": "PLAYER", "points_scored": 45, "remaining_points": 398, "darts_thrown": 3, "fields": ""}, {"player": "Rhys Evans", "points_scored": 15, "remaining_points": 451, "darts_thrown": 3, "fields": "5,5,5"}, {"player": "PLAYER", "points_scored": 60, "remaining_points": 338, "darts_thrown": 3, "fields": ""}, {"player": "Rhys Evans", "points_scored": 30, "remaining_points": 421, "darts_thrown": 3, "fields": "5,20,5"}, {"player": "PLAYER", "points_scored": 30, "remaining_points": 308, "darts_thrown": 3, "fields": ""}, {"player": "Rhys Evans", "points_scored": 43, "remaining_points": 378, "darts_thrown": 3, "fields": "5,20,18"}, {"player": "PLAYER", "points_scored": 44, "remaining_points": 264, "darts_thrown": 3, "fields": ""}, {"player": "Rhys Evans", "points_scored": 21, "remaining_points": 357, "darts_thrown": 3, "fields": "5,1,T5"}, {"player": "PLAYER", "points_scored": 51, "remaining_points": 213, "darts_thrown": 3, "fields": ""}, {"player": "Rhys Evans", "points_scored": 14, "remaining_points": 343, "darts_thrown": 3, "fields": "1,12,1"}, {"player": "PLAYER", "points_scored": 32, "remaining_points": 181, "darts_thrown": 3, "fields": ""}, {"player": "Rhys Evans", "points_scored": 45, "remaining_points": 298, "darts_thrown": 3, "fields": "20,20,5"}, {"player": "PLAYER", "points_scored": 26, "remaining_points": 155, "darts_thrown": 3, "fields": ""}, {"player": "Rhys Evans", "points_scored": 58, "remaining_points": 240, "darts_thrown": 3, "fields": "20,18,20"}, {"player": "PLAYER", "points_scored": 60, "remaining_points": 95, "darts_thrown": 3, "fields": ""}, {"player": "Rhys Evans", "points_scored": 36, "remaining_points": 204, "darts_thrown": 3, "fields": "T5,1,20"}, {"player": "PLAYER", "points_scored": 30, "remaining_points": 65, "darts_thrown": 3, "fields": ""}, {"player": "Rhys Evans", "points_scored": 45, "remaining_points": 159, "darts_thrown": 3, "fields": "20,5,20"}, {"player": "PLAYER", "points_scored": 31, "remaining_points": 34, "darts_thrown": 3, "fields": ""}, {"player": "Rhys Evans", "points_scored": 41, "remaining_points": 118, "darts_thrown": 3, "fields": "20,1,20"}, {"player": "PLAYER", "points_scored": 0, "remaining_points": 34, "darts_thrown": 3, "fields": ""}, {"player": "Rhys Evans", "points_scored": 32, "remaining_points": 86, "darts_thrown": 3, "fields": "5,20,7"}, {"player": "PLAYER", "points_scored": 17, "remaining_points": 17, "darts_thrown": 3, "fields": ""}, {"player": "Rhys Evans", "points_scored": 38, "remaining_points": 48, "darts_thrown": 3, "fields": "18,4,16"}, {"player": "PLAYER", "points_scored": 0, "remaining_points": 17, "darts_thrown": 3, "fields": ""}, {"player": "Rhys Evans", "points_scored": 24, "remaining_points": 24, "darts_thrown": 3, "fields": "T8,0,0"}, {"player": "PLAYER", "points_scored": 1, "remaining_points": 16, "darts_thrown": 3, "fields": ""}, {"player": "Rhys Evans", "points_scored": 18, "remaining_points": 6, "darts_thrown": 3, "fields": "12,0,6"}, {"player": "PLAYER", "points_scored": 16, "remaining_points": 0, "darts_thrown": 1, "fields": ""}], [{"player": "Rhys Evans", "points_scored": 41, "remaining_points": 460, "darts_thrown": 3, "fields": "1,20,20"}, {"player": "PLAYER", "points_scored": 31, "remaining_points": 470, "darts_thrown": 3, "fields": ""}, {"player": "Rhys Evans", "points_scored": 9, "remaining_points": 451, "darts_thrown": 3, "fields": "1,T1,5"}, {"player": "PLAYER", "points_scored": 85, "remaining_points": 385, "darts_thrown": 3, "fields": ""}, {"player": "Rhys Evans", "points_scored": 58, "remaining_points": 393, "darts_thrown": 3, "fields": "18,20,20"}, {"player": "PLAYER", "points_scored": 61, "remaining_points": 324, "darts_thrown": 3, "fields": ""}, {"player": "Rhys Evans", "points_scored": 60, "remaining_points": 333, "darts_thrown": 3, "fields": "20,20,20"}, {"player": "PLAYER", "points_scored": 60, "remaining_points": 264, "darts_thrown": 3, "fields": ""}, {"player": "Rhys Evans", "points_scored": 22, "remaining_points": 311, "darts_thrown": 3, "fields": "1,20,1"}, {"player": "PLAYER", "points_scored": 13, "remaining_points": 251, "darts_thrown": 3, "fields": ""}, {"player": "Rhys Evans", "points_scored": 37, "remaining_points": 274, "darts_thrown": 3, "fields": "5,12,20"}, {"player": "PLAYER", "points_scored": 45, "remaining_points": 206, "darts_thrown": 3, "fields": ""}, {"player": "Rhys Evans", "points_scored": 28, "remaining_points": 246, "darts_thrown": 3, "fields": "5,T1,20"}, {"player": "PLAYER", "points_scored": 19, "remaining_points": 187, "darts_thrown": 3, "fields": ""}, {"player": "Rhys Evans", "points_scored": 21, "remaining_points": 225, "darts_thrown": 3, "fields": "1,5,T5"}, {"player": "PLAYER", "points_scored": 49, "remaining_points": 138, "darts_thrown": 3, "fields": ""}, {"player": "Rhys Evans", "points_scored": 25, "remaining_points": 200, "darts_thrown": 3, "fields": "5,0,20"}, {"player": "PLAYER", "points_scored": 33, "remaining_points": 105, "darts_thrown": 3, "fields": ""}, {"player": "Rhys Evans", "points_scored": 41, "remaining_points": 159, "darts_thrown": 3, "fields": "20,20,1"}, {"player": "PLAYER", "points_scored": 70, "remaining_points": 35, "darts_thrown": 3, "fields": ""}, {"player": "Rhys Evans", "points_scored": 45, "remaining_points": 114, "darts_thrown": 3, "fields": "5,20,20"}, {"player": "PLAYER", "points_scored": 19, "remaining_points": 16, "darts_thrown": 3, "fields": ""}, {"player": "Rhys Evans", "points_scored": 30, "remaining_points": 84, "darts_thrown": 3, "fields": "5,7,18"}, {"player": "PLAYER", "points_scored": 0, "remaining_points": 16, "darts_thrown": 3, "fields": ""}, {"player": "Rhys Evans", "points_scored": 68, "remaining_points": 16, "darts_thrown": 3, "fields": "0,8,T20"}, {"player": "PLAYER", "points_scored": 8, "remaining_points": 8, "darts_thrown": 3, "fields": ""}, {"player": "Rhys Evans", "points_scored": 16, "remaining_points": 0, "darts_thrown": 1, "fields": "D8"}], [{"player": "PLAYER", "points_scored": 17, "remaining_points": 484, "darts_thrown": 3, "fields": ""}, {"player": "Rhys Evans", "points_scored": 95, "remaining_points": 406, "darts_thrown": 3, "fields": "T20,T5,20"}, {"player": "PLAYER", "points_scored": 45, "remaining_points": 439, "darts_thrown": 3, "fields": ""}, {"player": "Rhys Evans", "points_scored": 83, "remaining_points": 323, "darts_thrown": 3, "fields": "T20,18,5"}, {"player": "PLAYER", "points_scored": 11, "remaining_points": 428, "darts_thrown": 3, "fields": ""}, {"player": "Rhys Evans", "points_scored": 22, "remaining_points": 301, "darts_thrown": 3, "fields": "1,20,1"}, {"player": "PLAYER", "points_scored": 10, "remaining_points": 418, "darts_thrown": 3, "fields": ""}, {"player": "Rhys Evans", "points_scored": 81, "remaining_points": 220, "darts_thrown": 3, "fields": "T20,1,20"}, {"player": "PLAYER", "points_scored": 70, "remaining_points": 348, "darts_thrown": 3, "fields": ""}, {"player": "Rhys Evans", "points_scored": 22, "remaining_points": 198, "darts_thrown": 3, "fields": "5,12,5"}, {"player": "PLAYER", "points_scored": 25, "remaining_points": 323, "darts_thrown": 3, "fields": ""}, {"player": "Rhys Evans", "points_scored": 26, "remaining_points": 172, "darts_thrown": 3, "fields": "20,1,5"}, {"player": "PLAYER", "points_scored": 43, "remaining_points": 280, "darts_thrown": 3, "fields": ""}, {"player": "Rhys Evans", "points_scored": 28, "remaining_points": 144, "darts_thrown": 3, "fields": "T1,20,5"}, {"player": "PLAYER", "points_scored": 28, "remaining_points": 252, "darts_thrown": 3, "fields": ""}, {"player": "Rhys Evans", "points_scored": 28, "remaining_points": 116, "darts_thrown": 3, "fields": "5,T1,20"}, {"player": "PLAYER", "points_scored": 66, "remaining_points": 186, "darts_thrown": 3, "fields": ""}, {"player": "Rhys Evans", "points_scored": 60, "remaining_points": 56, "darts_thrown": 3, "fields": "20,20,20"}, {"player": "PLAYER", "points_scored": 29, "remaining_points": 157, "darts_thrown": 3, "fields": ""}, {"player": "Rhys Evans", "points_scored": 36, "remaining_points": 20, "darts_thrown": 3, "fields": "16,20,0"}, {"player": "PLAYER", "points_scored": 92, "remaining_points": 65, "darts_thrown": 3, "fields": ""}, {"player": "Rhys Evans", "points_scored": 0, "remaining_points": 20, "darts_thrown": 3, "fields": "6,D19"}, {"player": "PLAYER", "points_scored": 0, "remaining_points": 65, "darts_thrown": 3, "fields": ""}, {"player": "Rhys Evans", "points_scored": 20, "remaining_points": 0, "darts_thrown": 1, "fields": "D10"}]]}